Lab 08/ALU/ALU.v
module ALU(input wire [3:0] a, b,
           input wire [2:0] f,
           output reg [3:0] y);

    always @ (a or b or f) begin
        
        case(f)
            3'b000: y = (a & b); //AND
            3'b001: y = (a | b); //OR
            3'b010: y = (a + b); //Suma
            3'b100: y = (a & ~b); //AND, con NOT B
            3'b101: y = (a | ~b); //OR, con NOT B
            3'b110: y = (a - b); //Resta
            3'b111: y = (a < b) ? 1:0; //Comparacion entre A y B
            default: y = 3'b0; //Valor por defecto por si la 
                               //opción no se encuentra en la ALU
        endcase

    end


endmodule

Lab 08/ALU/ALU_tb.v
module testbench();

    reg [3:0] a, b;
    reg [2:0] f;
    wire [3:0] y;

    ALU m(a, b, f, y);


    initial begin
    $display("Ejerccio 3: ALU");
    $display("A | B | F | Salida");
    $monitor("%b | %b | %b | %b", a, b, f, y);

       a = 4'b0000; b = 4'b0000; f = 3'b000;
    #1 a = 4'b0001; b = 4'b0000; f = 3'b000;
    #1 a = 4'b0001; b = 4'b0001; f = 3'b000;
    #1 a = 4'b0000; b = 4'b0000; f = 3'b001;
    #1 a = 4'b0000; b = 4'b0001; f = 3'b001;
    #1 a = 4'b0001; b = 4'b0001; f = 3'b001;
    #1 a = 4'b1000; b = 4'b0100; f = 3'b010;
    #1 a = 4'b0010; b = 4'b0000; f = 3'b100;
    #1 a = 4'b0000; b = 4'b0000; f = 3'b101;
    #1 a = 4'b0110; b = 4'b0001; f = 3'b110;
    #1 a = 4'b0100; b = 4'b0000; f = 3'b111;
    #1 a = 4'b0000; b = 4'b0100; f = 3'b111;

    end

    initial
        #30 $finish;

    initial begin
        $dumpfile("ALU_tb.vcd");
        $dumpvars(0, testbench);
    end


endmodule

Lab 08/ALU/ALU_tb.vcd
$date
	Sat Oct 24 21:32:24 2020
$end
$version
	Icarus Verilog
$end
$timescale
	1ps
$end
$scope module testbench $end
$var wire 4 ! y [3:0] $end
$var reg 4 " a [3:0] $end
$var reg 4 # b [3:0] $end
$var reg 3 $ f [2:0] $end
$scope module m $end
$var wire 4 % a [3:0] $end
$var wire 4 & b [3:0] $end
$var wire 3 ' f [2:0] $end
$var reg 4 ( y [3:0] $end
$upscope $end
$upscope $end
$enddefinitions $end
#0
$dumpvars
b0 (
b0 '
b0 &
b0 %
b0 $
b0 #
b0 "
b0 !
$end
#1
b1 "
b1 %
#2
b1 !
b1 (
b1 #
b1 &
#3
b0 !
b0 (
b1 $
b1 '
b0 #
b0 &
b0 "
b0 %
#4
b1 !
b1 (
b1 #
b1 &
#5
b1 "
b1 %
#6
b1100 !
b1100 (
b10 $
b10 '
b100 #
b100 &
b1000 "
b1000 %
#7
b10 !
b10 (
b100 $
b100 '
b0 #
b0 &
b10 "
b10 %
#8
b1111 !
b1111 (
b101 $
b101 '
b0 "
b0 %
#9
b101 !
b101 (
b110 $
b110 '
b1 #
b1 &
b110 "
b110 %
#10
b0 !
b0 (
b111 $
b111 '
b0 #
b0 &
b100 "
b100 %
#11
b1 !
b1 (
b100 #
b100 &
b0 "
b0 %
