Lab 10/Eje 2/Eje2.v
module ALU(input wire [3:0] a, b,
           input wire [2:0] f,
           output reg [3:0] y,
           output reg carry, zero);

    reg [4:0] c;
    always @ (a or b or f) begin

        case(f)
            3'b000: begin
              c = 5'b0;
              c = a; //Deja pasar lo que este en el Accumulador
              carry = (c[4] == 1) ? 1:0; //Si el bit mas significativo es 1 carry = on
              zero = (c[4] == 0) ? 1:0; //SI el bit mas significativo es 0 zero = on
              y = c[3:0];
              end

            3'b001: begin
              c = 5'b0;
              c = (a - b); //Resta de A menos B
              carry = (c[4] == 1) ? 1:0; //Si el bit mas significativo es 1 carry = on
              zero = (c[4] == 0) ? 1:0; //SI el bit mas significativo es 0 zero = on
              y = c[3:0];
              end

            3'b010: begin
              c = 5'b0;
              c = b; //Deja pasar lo que este en B
              carry = (c[4] == 1) ? 1:0; //Si el bit mas significativo es 1 carry = on
              zero = (c[4] == 0) ? 1:0; //SI el bit mas significativo es 0 zero = on
              y = c[3:0];
              end

            3'b011: begin
              c = 5'b0;
              c = (a + b); //Suma de A mas B
              carry = (c[4] == 1) ? 1:0; //Si el bit mas significativo es 1 carry = on
              zero = (c[4] == 0) ? 1:0; //SI el bit mas significativo es 0 zero = on
              y = c[3:0];
              end

            3'b100: begin
              c = 5'b0;
              c = ~(a & b); //NAND entre A y B
              carry = (c[4] == 1) ? 1:0; //Si el bit mas significativo es 1 carry = on
              zero = (c[4] == 0) ? 1:0; //SI el bit mas significativo es 0 zero = on
              y = c[3:0];
              end

            default: y = 3'b0; //Valor por defecto por si la
                               //opción no se encuentra en la ALU
        endcase
    end
endmodule

module buftri(input wire en, input wire [3:0]in, output wire [3:0]out);

  assign out = (en == 1) ? in :
               (en == 0) ? 4'bz : 4'bx;

endmodule

module Accu(input clk, input reset, input en, input [3:0] d, output reg [3:0] q);

  always @ (posedge clk, posedge reset) begin
  if (reset) q <= 4'b0;
  else if (en) q <= d;
  end

endmodule

module eje2(input clk, reset, input [2:0] en, f, input [3:0] b, output carry, zero, output [3:0] y);

  wire [3:0] data_bus, cable1, cable2;

  buftri a1(en[2], b, data_bus);
  ALU a2(cable2, data_bus, f, cable1, carry, zero);
  Accu a3(clk, reset, en[0], cable1, cable2);
  buftri a4(en[1], cable1, y);

endmodule

Lab 10/Eje 2/Eje2_tb.v
module testbench();

  reg clk, reset;
  reg [2:0] en, f;
  reg [3:0] b;
  wire carry, zero;
  wire [3:0] y;

  eje2 a1(clk, reset, en, f, b, carry, zero, y);

  initial begin
  #1

  clk = 0; en[2] = 1; en[1] = 1; en[0] = 1; b = 4'b0; f = 3'b010;
  reset = 0;
  $display("Ejercicio 2: Lab 10");
  $display("B | Y | C | Z");
  $monitor("%b | %b | %b | %b", b, y, carry, zero);
  #1 reset = 1;
  #1 reset = 0; f = 3'b010; b = 4'b1111;
  #1 f = 3'b000; b = 4'b0001;
  #1 f = 3'b001; b = 4'b0101;
  #1 f = 3'b011; b = 4'b0100;
  #1 f = 3'b100; b = 4'b0000;

  #30 $finish;
  end

  always
  begin
    #1 clk = ~clk;
    end

    initial begin
      $dumpfile("Eje2_tb.vcd");
      $dumpvars(0, testbench);
    end

endmodule

Lab 10/Eje 2/Eje2_tb.vcd
$date
	Sat Nov 07 19:18:07 2020
$end
$version
	Icarus Verilog
$end
$timescale
	1ps
$end
$scope module testbench $end
$var wire 1 ! zero $end
$var wire 4 " y [3:0] $end
$var wire 1 # carry $end
$var reg 4 $ b [3:0] $end
$var reg 1 % clk $end
$var reg 3 & en [2:0] $end
$var reg 3 ' f [2:0] $end
$var reg 1 ( reset $end
$scope module a1 $end
$var wire 4 ) b [3:0] $end
$var wire 1 % clk $end
$var wire 3 * en [2:0] $end
$var wire 3 + f [2:0] $end
$var wire 1 ( reset $end
$var wire 1 ! zero $end
$var wire 4 , y [3:0] $end
$var wire 4 - data_bus [3:0] $end
$var wire 1 # carry $end
$var wire 4 . cable2 [3:0] $end
$var wire 4 / cable1 [3:0] $end
$scope module a1 $end
$var wire 1 0 en $end
$var wire 4 1 in [3:0] $end
$var wire 4 2 out [3:0] $end
$upscope $end
$scope module a2 $end
$var wire 4 3 b [3:0] $end
$var wire 3 4 f [2:0] $end
$var wire 4 5 a [3:0] $end
$var reg 5 6 c [4:0] $end
$var reg 1 # carry $end
$var reg 4 7 y [3:0] $end
$var reg 1 ! zero $end
$upscope $end
$scope module a3 $end
$var wire 1 % clk $end
$var wire 4 8 d [3:0] $end
$var wire 1 9 en $end
$var wire 1 ( reset $end
$var reg 4 : q [3:0] $end
$upscope $end
$scope module a4 $end
$var wire 1 ; en $end
$var wire 4 < in [3:0] $end
$var wire 4 = out [3:0] $end
$upscope $end
$upscope $end
$upscope $end
$enddefinitions $end
#0
$dumpvars
bx =
bx <
x;
bx :
x9
bx 8
bx 7
bx 6
bx 5
bx 4
bx 3
bx 2
bx 1
x0
bx /
bx .
bx -
bx ,
bx +
bx *
bx )
x(
bx '
bx &
x%
bx $
x#
bx "
x!
$end
#1
b0 .
b0 5
b0 :
b0 "
b0 ,
b0 =
b0 /
b0 7
b0 8
b0 <
1!
0#
b0 6
b0 -
b0 2
b0 3
19
1;
10
0(
b10 '
b10 +
b10 4
b0 $
b0 )
b0 1
b111 &
b111 *
1%
#2
0%
1(
#3
b1111 "
b1111 ,
b1111 =
b1111 /
b1111 7
b1111 8
b1111 <
b1111 6
b1111 -
b1111 2
b1111 3
1%
b1111 $
b1111 )
b1111 1
0(
#4
b0 "
b0 ,
b0 =
b1 -
b1 2
b1 3
b0 /
b0 7
b0 8
b0 <
b0 6
0%
b1 $
b1 )
b1 1
b0 '
b0 +
b0 4
#5
b1111 .
b1111 5
b1111 :
b1010 "
b1010 ,
b1010 =
b101 -
b101 2
b101 3
b1010 /
b1010 7
b1010 8
b1010 <
1!
0#
b1010 6
1%
b101 $
b101 )
b101 1
b1 '
b1 +
b1 4
#6
b11 "
b11 ,
b11 =
b100 -
b100 2
b100 3
b11 /
b11 7
b11 8
b11 <
0!
1#
b10011 6
0%
b100 $
b100 )
b100 1
b11 '
b11 +
b11 4
#7
b1011 .
b1011 5
b1011 :
b1111 "
b1111 ,
b1111 =
b0 -
b0 2
b0 3
b1111 /
b1111 7
b1111 8
b1111 <
b11111 6
1%
b0 $
b0 )
b0 1
b100 '
b100 +
b100 4
#8
0%
#9
b11111 6
b1111 .
b1111 5
b1111 :
1%
