Lab 04/Alarma/Alarma.v

module alarmakarnough(input wire A, B, C, output wire Y);

  not (n1, A);
  and (n2, n1, C);
  and (n3, B, C);
  or  (Y, n2, n3);

endmodule

module alarmaPOS(input wire A, B, C, output wire Y);

  assign Y = (A | B | C) & (A | ~B | C) & (~A | B | C) & (~A | B | ~C) & (~A | ~B | C);

endmodule

module alarmaSOP(input wire A, B, C, output wire Y);

  assign Y = (~A & ~B & C) | (~A & B & C) | (A & B & C);

endmodule

Lab 04/Alarma/Alarma_tb.v
module testbench();

  reg p1, p2, p3, p4, p5, p6, p7, p8, p9;
  wire s1, s2, s3;

  alarmakarnough a1(p1, p2, p3, s1);
  alarmaPOS a2(p4, p5, p6, s2);
  alarmaSOP a3(p7, p8, p9, s3);


  initial begin

    $display("Ejercicio 5 Mapa de Karnough");
    $display("A B C | Y");
    $monitor("%b %b %b  | %b", p1, p2, p3, s1);

       p1 = 0; p2 = 0; p3 = 0;
    #1 p1 = 0; p2 = 0; p3 = 1;
    #1 p1 = 0; p2 = 1; p3 = 0;
    #1 p1 = 0; p2 = 1; p3 = 1;
    #1 p1 = 1; p2 = 0; p3 = 0;
    #1 p1 = 1; p2 = 0; p3 = 1;
    #1 p1 = 1; p2 = 1; p3 = 0;
    #1 p1 = 1; p2 = 1; p3 = 1;

  end

  initial begin

    #9

    $display("\n");
    $display("Ejercicio 5 POS");
    $display("A B C | Y");
    $monitor("%b %b %b  | %b", p4, p5, p6, s2);

       p4 = 0; p5 = 0; p6 = 0;
    #1 p4 = 0; p5 = 0; p6 = 1;
    #1 p4 = 0; p5 = 1; p6 = 0;
    #1 p4 = 0; p5 = 1; p6 = 1;
    #1 p4 = 1; p5 = 0; p6 = 0;
    #1 p4 = 1; p5 = 0; p6 = 1;
    #1 p4 = 1; p5 = 1; p6 = 0;
    #1 p4 = 1; p5 = 1; p6 = 1;

  end

  initial begin

    #18

    $display("\n");
    $display("Ejercicio 5 SOP");
    $display("A B C | Y");
    $monitor("%b %b %b  | %b", p7, p8, p9, s3);

       p7 = 0; p8 = 0; p9 = 0;
    #1 p7 = 0; p8 = 0; p9 = 1;
    #1 p7 = 0; p8 = 1; p9 = 0;
    #1 p7 = 0; p8 = 1; p9 = 1;
    #1 p7 = 1; p8 = 0; p9 = 0;
    #1 p7 = 1; p8 = 0; p9 = 1;
    #1 p7 = 1; p8 = 1; p9 = 0;
    #1 p7 = 1; p8 = 1; p9 = 1;

  end

  initial

    #27 $finish;

  initial begin

    $dumpfile("Alarma_tb.vcd");
    $dumpvars(0, testbench);

  end

endmodule

Lab 04/Alarma/Alarma_tb.vcd
$date
	Sat Aug 08 20:04:54 2020
$end
$version
	Icarus Verilog
$end
$timescale
	1ps
$end
$scope module testbench $end
$var wire 1 ! s3 $end
$var wire 1 " s2 $end
$var wire 1 # s1 $end
$var reg 1 $ p1 $end
$var reg 1 % p2 $end
$var reg 1 & p3 $end
$var reg 1 ' p4 $end
$var reg 1 ( p5 $end
$var reg 1 ) p6 $end
$var reg 1 * p7 $end
$var reg 1 + p8 $end
$var reg 1 , p9 $end
$scope module a1 $end
$var wire 1 $ A $end
$var wire 1 % B $end
$var wire 1 & C $end
$var wire 1 # Y $end
$var wire 1 - n1 $end
$var wire 1 . n2 $end
$var wire 1 / n3 $end
$upscope $end
$scope module a2 $end
$var wire 1 ' A $end
$var wire 1 ( B $end
$var wire 1 ) C $end
$var wire 1 " Y $end
$upscope $end
$scope module a3 $end
$var wire 1 * A $end
$var wire 1 + B $end
$var wire 1 , C $end
$var wire 1 ! Y $end
$upscope $end
$upscope $end
$enddefinitions $end
#0
$dumpvars
0/
0.
1-
x,
x+
x*
x)
x(
x'
0&
0%
0$
0#
x"
x!
$end
#1
1#
1.
1&
#2
0#
0.
0&
1%
#3
1#
1.
1/
1&
#4
0#
0.
0/
0-
0&
0%
1$
#5
1&
#6
0&
1%
#7
1#
1/
1&
#9
0"
0)
0(
0'
#10
1"
1)
#11
0"
0)
1(
#12
1"
1)
#13
0"
0)
0(
1'
#14
1)
#15
0)
1(
#16
1"
1)
#18
0!
0,
0+
0*
#19
1!
1,
#20
0!
0,
1+
#21
1!
1,
#22
0!
0,
0+
1*
#23
1,
#24
0,
1+
#25
1!
1,
