Lab 09/Eje 01/Eje_01.v
module ffd(input clk, input reset, input en, input d, output reg q);

  always @ (posedge clk, posedge reset)
  if (reset) q <= 1'b0;
  else if (en == 1) q <= d;

endmodule

module ffd2(input clk, reset, en, input [1:0] d, output [1:0] q);

  ffd a0(clk, reset, en, d[0], q[0]);
  ffd a1(clk, reset, en, d[1], q[1]);

endmodule

module ffd4(input clk, reset, en, input [3:0] d, output [3:0] q);

  ffd a0(clk, reset, en, d[0], q[0]);
  ffd a1(clk, reset, en, d[1], q[1]);
  ffd a2(clk, reset, en, d[2], q[2]);
  ffd a3(clk, reset, en, d[3], q[3]);

endmodule

Lab 09/Eje 01/Eje_01_tb.v
module testbench();

  reg clk, reset, en, d;
  reg [1:0] d1;
  reg [3:0] d2;
  wire q;
  wire [1:0] q1;
  wire [3:0] q2;

  ffd a1(clk, reset, en, d, q);
  ffd2 a2(clk, reset, en, d1, q1);
  ffd4 a3(clk, reset, en, d2, q2);

  //FF de 1 bit
  initial begin

  #1
  clk = 0; en = 1; reset = 0; d = 0; d1 = 2'b00; d2 = 4'b0000;
  $display("Ejercicio 01");
  $display("| D | Q | 1 bit | D  | Q  | 2 bits | D    | Q    | 4 bits ");
  $monitor("| %b | %b |       | %b | %b |        | %b | %b |", d, q, d1, q1, d2, q2);

  #1 reset = 1;
  #1 reset = 0;
  #1 d = 1; d1 = 2'b10; d2 = 4'b1010;
  #4 d = 0; d1 = 2'b11; d2 = 4'b1110;
  #2 en = 0;
  #4 d = 1; d1 = 2'b01; d2 = 4'b1001;

  #20 $finish;
  end

  always
  begin
    #1 clk = ~clk;
    end

  initial begin
    $dumpfile("Eje_01_tb.vcd");
    $dumpvars(0, testbench);
  end


endmodule

Lab 09/Eje 01/Eje_01_tb.vcd
$date
	Fri Oct 30 21:39:39 2020
$end
$version
	Icarus Verilog
$end
$timescale
	1ps
$end
$scope module testbench $end
$var wire 4 ! q2 [3:0] $end
$var wire 2 " q1 [1:0] $end
$var wire 1 # q $end
$var reg 1 $ clk $end
$var reg 1 % d $end
$var reg 2 & d1 [1:0] $end
$var reg 4 ' d2 [3:0] $end
$var reg 1 ( en $end
$var reg 1 ) reset $end
$scope module a1 $end
$var wire 1 $ clk $end
$var wire 1 % d $end
$var wire 1 ( en $end
$var wire 1 ) reset $end
$var reg 1 # q $end
$upscope $end
$scope module a2 $end
$var wire 1 $ clk $end
$var wire 2 * d [1:0] $end
$var wire 1 ( en $end
$var wire 1 ) reset $end
$var wire 2 + q [1:0] $end
$scope module a0 $end
$var wire 1 $ clk $end
$var wire 1 , d $end
$var wire 1 ( en $end
$var wire 1 ) reset $end
$var reg 1 - q $end
$upscope $end
$scope module a1 $end
$var wire 1 $ clk $end
$var wire 1 . d $end
$var wire 1 ( en $end
$var wire 1 ) reset $end
$var reg 1 / q $end
$upscope $end
$upscope $end
$scope module a3 $end
$var wire 1 $ clk $end
$var wire 4 0 d [3:0] $end
$var wire 1 ( en $end
$var wire 1 ) reset $end
$var wire 4 1 q [3:0] $end
$scope module a0 $end
$var wire 1 $ clk $end
$var wire 1 2 d $end
$var wire 1 ( en $end
$var wire 1 ) reset $end
$var reg 1 3 q $end
$upscope $end
$scope module a1 $end
$var wire 1 $ clk $end
$var wire 1 4 d $end
$var wire 1 ( en $end
$var wire 1 ) reset $end
$var reg 1 5 q $end
$upscope $end
$scope module a2 $end
$var wire 1 $ clk $end
$var wire 1 6 d $end
$var wire 1 ( en $end
$var wire 1 ) reset $end
$var reg 1 7 q $end
$upscope $end
$scope module a3 $end
$var wire 1 $ clk $end
$var wire 1 8 d $end
$var wire 1 ( en $end
$var wire 1 ) reset $end
$var reg 1 9 q $end
$upscope $end
$upscope $end
$upscope $end
$enddefinitions $end
#0
$dumpvars
x9
x8
x7
x6
x5
x4
x3
x2
bx 1
bx 0
x/
x.
x-
x,
bx +
bx *
x)
x(
bx '
bx &
x%
x$
x#
bx "
bx !
$end
#1
0#
0-
b0 "
b0 +
0/
03
05
07
b0 !
b0 1
09
02
04
06
08
0,
0.
b0 '
b0 0
b0 &
b0 *
0%
0)
1(
1$
#2
0$
1)
#3
1$
0)
#4
14
18
1.
0$
b1010 '
b1010 0
b10 &
b10 *
1%
#5
19
b1010 !
b1010 1
15
b10 "
b10 +
1/
1#
1$
#6
0$
#7
1$
#8
16
1,
0$
b1110 '
b1110 0
b11 &
b11 *
0%
#9
b1110 !
b1110 1
17
b11 "
b11 +
1-
0#
1$
#10
0$
0(
#11
1$
#12
0$
#13
1$
#14
12
04
06
0.
0$
b1001 '
b1001 0
b1 &
b1 *
1%
