Lab 08/Memory/memory.v
//Ejercicio 2 Laboratortio 8 Electronica Digital 1

module memoria(input wire [11:0] l, output wire [7:0] y); 
        //Definimos las variables de entrada y salida.

    reg [7:0] m[0:4095]; //Asignamos el tamaño de la memoria
                        //la cual es de 4k con 8 bits de ancho

    initial begin
        $readmemb("memoria.ejercicio_2", m); //guardamos un valor 
            //binario en la memoria
    end

    assign y = m[l]; 

endmodule

Lab 08/Memory/memory_tb.v
module testbench();

    reg [11:0] l;
    wire [7:0] y;

    memoria a(l, y);

    initial begin
        $display("Ejercicio 2: Memoria ROM");
        $display("-Localidad- |----Dato----");
        $monitor("%b | %b", l, y);

        #1 l = 12'b000000000000;
        #1 l = 12'b000000000001;
        #1 l = 12'b000000000010;
        #1 l = 12'b000000000011;
        #1 l = 12'b000000000100;
        #1 l = 12'b000000000101;
        #1 l = 12'b000000000110;
        #1 l = 12'b000000000111;
        #1 l = 12'b000000001000;
        #1 l = 12'b000000001001;

    end

    initial
    #100 $finish;

    initial begin
        $dumpfile("memory_tb.vcd");
        $dumpvars(0, testbench);
    end


endmodule

Lab 08/Memory/memory_tb.vcd
$date
	Sat Oct 24 21:47:40 2020
$end
$version
	Icarus Verilog
$end
$timescale
	1ps
$end
$scope module testbench $end
$var wire 8 ! y [7:0] $end
$var reg 12 " l [11:0] $end
$scope module a $end
$var wire 12 # l [11:0] $end
$var wire 8 $ y [7:0] $end
$upscope $end
$upscope $end
$enddefinitions $end
#0
$dumpvars
bx $
bx #
bx "
bx !
$end
#1
b0 !
b0 $
b0 "
b0 #
#2
b10001 !
b10001 $
b1 "
b1 #
#3
b110000 !
b110000 $
b10 "
b10 #
#4
b11111111 !
b11111111 $
b11 "
b11 #
#5
b10100101 !
b10100101 $
b100 "
b100 #
#6
b11000011 !
b11000011 $
b101 "
b101 #
#7
b100000 !
b100000 $
b110 "
b110 #
#8
b11101110 !
b11101110 $
b111 "
b111 #
#9
b10011111 !
b10011111 $
b1000 "
b1000 #
#10
b10100000 !
b10100000 $
b1001 "
b1001 #
