Lab 10/Eje 1/Eje1.v
module ffd4(input clk, input reset, input en, input [3:0] d, output reg [3:0] q);

  always @ (posedge clk, posedge reset) begin
  if (reset) q <= 4'b0;
  else if (en) q <= d;
  end

endmodule

module fetch(input clk, reset, en, input [7:0] program_byte, output [3:0] instr, oprnd);

  ffd4 f1(clk, reset, en, program_byte[7:4], instr); 
  ffd4 f2(clk, reset, en, program_byte[3:0], oprnd);

endmodule

module ROM(input wire [11:0] PC, output wire [7:0] program_byte);
        //Definimos las variables de entrada y salida.

    reg [7:0] m[0:4095]; //Asignamos el tamaño de la memoria
                        //la cual es de 4k con 8 bits de ancho

    initial begin
        $readmemb("memoria.lab10", m); //guardamos un valor
            //binario en la memoria
    end

    assign program_byte = m[PC];

endmodule

module counter #(parameter N = 12) //Definimos variables
                (input wire clk, reset, en, load,
                 input wire [N-1:0] val,
                 output reg [N-1:0] q);

  always @ (posedge clk or posedge load or posedge reset) begin
    if (reset == 1) //flanco de reloj se colocara la salida en 0
      q <= 12'b0;

    else if (load == 1)//flando de reloj se cargara un valor al
      q <= val;        //contador

    else if (en == 1)//cuando enable sea igual a 1
      q <= q + 1;   //comenzara a contar

  end

endmodule

module Eje1(input reset, en1, en2, load, clk, input [11:0] val, output [7:0] program_byte, output [3:0] instr, oprnd);

  wire [11:0] PC;

  counter a1(clk, reset, en1, load, val, PC);
  ROM a2(PC, program_byte);
  fetch a3(clk, reset, en2, program_byte, instr, oprnd);

endmodule

Lab 10/Eje 1/Eje1_tb.v
module testbench();

  reg reset, en1, en2, load, clk;
  reg [11:0] val;
  wire [7:0] program_byte;
  wire [3:0] instr, oprnd;

  Eje1 a1(reset, en1, en2, load, clk, val, program_byte, instr, oprnd);

  initial begin
    #1

    clk = 0; en1 = 1; en2 = 1; val = 12'b0; reset = 0;

    $display("Ejercicio 1: lab 10");
    $display("Load         |program_byte| instr | oprnd");
    $monitor("%b |  %b  | %b  | %b", val, program_byte, instr, oprnd);

    #1 reset = 1;
    #1 reset = 0;


    #24 $finish;
    end

  always
  begin
    #1 clk = ~clk;
    end

    initial begin
      $dumpfile("Eje1_tb.vcd");
      $dumpvars(0, testbench);
    end

endmodule

Lab 10/Eje 1/Eje1_tb.vcd
$date
	Sat Nov 07 19:11:16 2020
$end
$version
	Icarus Verilog
$end
$timescale
	1ps
$end
$scope module testbench $end
$var wire 8 ! program_byte [7:0] $end
$var wire 4 " oprnd [3:0] $end
$var wire 4 # instr [3:0] $end
$var reg 1 $ clk $end
$var reg 1 % en1 $end
$var reg 1 & en2 $end
$var reg 1 ' load $end
$var reg 1 ( reset $end
$var reg 12 ) val [11:0] $end
$scope module a1 $end
$var wire 1 $ clk $end
$var wire 1 % en1 $end
$var wire 1 & en2 $end
$var wire 1 ' load $end
$var wire 1 ( reset $end
$var wire 12 * val [11:0] $end
$var wire 8 + program_byte [7:0] $end
$var wire 4 , oprnd [3:0] $end
$var wire 4 - instr [3:0] $end
$var wire 12 . PC [11:0] $end
$scope module a1 $end
$var wire 1 $ clk $end
$var wire 1 % en $end
$var wire 1 ' load $end
$var wire 1 ( reset $end
$var wire 12 / val [11:0] $end
$var reg 12 0 q [11:0] $end
$upscope $end
$scope module a2 $end
$var wire 12 1 PC [11:0] $end
$var wire 8 2 program_byte [7:0] $end
$upscope $end
$scope module a3 $end
$var wire 1 $ clk $end
$var wire 1 & en $end
$var wire 8 3 program_byte [7:0] $end
$var wire 1 ( reset $end
$var wire 4 4 oprnd [3:0] $end
$var wire 4 5 instr [3:0] $end
$scope module f1 $end
$var wire 1 $ clk $end
$var wire 4 6 d [3:0] $end
$var wire 1 & en $end
$var wire 1 ( reset $end
$var reg 4 7 q [3:0] $end
$upscope $end
$scope module f2 $end
$var wire 1 $ clk $end
$var wire 4 8 d [3:0] $end
$var wire 1 & en $end
$var wire 1 ( reset $end
$var reg 4 9 q [3:0] $end
$upscope $end
$upscope $end
$upscope $end
$upscope $end
$enddefinitions $end
#0
$dumpvars
bx 9
bx 8
bx 7
bx 6
bx 5
bx 4
bx 3
bx 2
bx 1
bx 0
bx /
bx .
bx -
bx ,
bx +
bx *
bx )
x(
x'
x&
x%
x$
bx #
bx "
bx !
$end
#1
0(
b0 )
b0 *
b0 /
1&
1%
1$
#2
b101 6
b1010 8
b1011010 !
b1011010 +
b1011010 2
b1011010 3
b0 .
b0 0
b0 1
b0 "
b0 ,
b0 4
b0 9
b0 #
b0 -
b0 5
b0 7
0$
1(
#3
b1111 6
b0 8
b11110000 !
b11110000 +
b11110000 2
b11110000 3
b1 .
b1 0
b1 1
b101 #
b101 -
b101 5
b101 7
b1010 "
b1010 ,
b1010 4
b1010 9
1$
0(
#4
0$
#5
b1100 6
b11 8
b11000011 !
b11000011 +
b11000011 2
b11000011 3
b10 .
b10 0
b10 1
b0 "
b0 ,
b0 4
b0 9
b1111 #
b1111 -
b1111 5
b1111 7
1$
#6
0$
#7
b0 6
b0 8
b0 !
b0 +
b0 2
b0 3
b11 .
b11 0
b11 1
b1100 #
b1100 -
b1100 5
b1100 7
b11 "
b11 ,
b11 4
b11 9
1$
#8
0$
#9
b1111 6
b1111 8
b11111111 !
b11111111 +
b11111111 2
b11111111 3
b100 .
b100 0
b100 1
b0 "
b0 ,
b0 4
b0 9
b0 #
b0 -
b0 5
b0 7
1$
#10
0$
#11
b1010 6
b1010 8
b10101010 !
b10101010 +
b10101010 2
b10101010 3
b101 .
b101 0
b101 1
b1111 #
b1111 -
b1111 5
b1111 7
b1111 "
b1111 ,
b1111 4
b1111 9
1$
#12
0$
#13
b0 6
b1111 8
b1111 !
b1111 +
b1111 2
b1111 3
b110 .
b110 0
b110 1
b1010 "
b1010 ,
b1010 4
b1010 9
b1010 #
b1010 -
b1010 5
b1010 7
1$
#14
0$
#15
b1100 6
b1100 8
b11001100 !
b11001100 +
b11001100 2
b11001100 3
b111 .
b111 0
b111 1
b0 #
b0 -
b0 5
b0 7
b1111 "
b1111 ,
b1111 4
b1111 9
1$
#16
0$
#17
b1 6
b1 8
b10001 !
b10001 +
b10001 2
b10001 3
b1000 .
b1000 0
b1000 1
b1100 "
b1100 ,
b1100 4
b1100 9
b1100 #
b1100 -
b1100 5
b1100 7
1$
#18
0$
#19
b1110 6
b0 8
b11100000 !
b11100000 +
b11100000 2
b11100000 3
b1001 .
b1001 0
b1001 1
b1 #
b1 -
b1 5
b1 7
b1 "
b1 ,
b1 4
b1 9
1$
#20
0$
#21
bx 6
bx 8
bx !
bx +
bx 2
bx 3
b1010 .
b1010 0
b1010 1
b0 "
b0 ,
b0 4
b0 9
b1110 #
b1110 -
b1110 5
b1110 7
1$
#22
0$
#23
b1011 .
b1011 0
b1011 1
bx #
bx -
bx 5
bx 7
bx "
bx ,
bx 4
bx 9
1$
#24
0$
#25
b1100 .
b1100 0
b1100 1
1$
#26
0$
#27
b1101 .
b1101 0
b1101 1
1$
