Lab 06/Lab_06.v
module ff(input clk, reset, d, output reg q);

  always @ (posedge clk, posedge reset)
    if (reset)
      q <= 1'b0;
    else
      q <= d;

endmodule

//Ejercicio 5
module ff_4(input clk, input reset, input en, input [3:0]d, output reg [3:0]q);

  always @ (posedge clk, posedge reset)
  if (reset) q <= 4'b0;
  else if (en) q <= d;

endmodule

//Ejercicio 1
module eje1 (input clk, reset, A, B, output wire y, output wire [1:0] S, SF);

  //Estado futuro combinacional
  assign SF[1] = (S[1] & A & B) | (S[0] & B);

  assign SF[0] = (~S[1] & ~S[0] & A);

  //Salida combinacional
  assign y = (S[1] & A & B);

  //Secuencial
  ff u1(clk, reset, SF[1], S[1]);
  ff u0(clk, reset, SF[0], S[0]);


endmodule

//Ejercicio 3
module gray(input clk, reset, co, output wire a, b, c, output wire [2:0] s, s_f);

  //salidas combinacional
  assign a = s[2];
  assign b = (~s[2] & s[1]) | (s[2] & ~s[1]);
  assign c = (s[1] & ~s[0]) | (~s[1] & s[0]);

  //estado futuro combinacional
  assign s_f[2] = (~s[2] & s[1] & s[0] & co) | (~s[2] & ~s[1] & ~s[0] & ~co) |
  (s[2] & s[0] & ~co) | (s[2] & ~s[1] & co) | (s[2] & s[1] & ~s[0]);

  assign s_f[1] = (s[1] & s[0] & ~co) | (~s[1] & s[0] & co) | (~s[1] & ~s[0] & ~co) |
  (s[1] & ~s[0] & co);

  assign s_f[0] = ~s[0];

  //estado secuencial
  ff S2(clk, reset, s_f[2], s[2]);
  ff S1(clk, reset, s_f[1], s[1]);
  ff S0(clk, reset, s_f[0], s[0]);

endmodule

Lab 06/Lab_06_tb.v
module testbench();

   reg clk, reset, en, v1, v2, co;
   reg [3:0] d;
   wire  [3:0] q;
   wire s1, A, B, C;
   wire [1:0] e, ef;
   wire [2:0] E, Ef;

   ff_4 a1(clk, reset, en, d, q);
   eje1 a2(clk, reset, v1, v2, s1, e, ef);
   gray a3(clk, reset, co, A, B, C, E, EF);

   //Ejercicio 5
   initial begin

    clk = 1;

    $display ("Ejercicio 5");
    $display ("-----------");
    $display ("-D-  | -Q-");
    $monitor("%b | %b", d, q);

    reset = 0; en = 1; d[3] = 0; d[2] = 0; d[1] = 0; d[0] = 0;
    #1 reset = 1;
    #1 reset = 0;
    #4 d[3] = 0; d[2] = 1; d[1] = 1; d[0] = 1;
    #4 d[3] = 1; d[2] = 1; d[1] = 0; d[0] = 1;
    #4 d[3] = 0; d[2] = 1; d[1] = 1; d[0] = 1;
    #4 d[3] = 0; d[2] = 1; d[1] = 0; d[0] = 0;
    #4 d[3] = 0; d[2] = 1; d[1] = 1; d[0] = 1;
    #4 d[3] = 1; d[2] = 1; d[1] = 0; d[0] = 0;
    #4 d[3] = 0; d[2] = 1; d[1] = 1; d[0] = 0;

    end

   //Ejercicio 1
   initial begin
    #40

    $display ("\n");
    $display ("Ejercicio 1, Mealy");
    $display ("------------------");
    $display ("A \t B | \t Y \t S \t Sf");
    $monitor ("%b \t %b | \t %b \t %b \t %b", v1, v2, s1, e, ef);

    reset = 0; v1 = 0; v2 = 0;
    #1 reset = 1;
    #1 reset = 0;
    #4 v1 = 1; v2 = 0;
    #8 v2 = 1;
    #16 v1 = 0; v2 = 0;
    #16 v1 = 1; v2 = 1;

   end

   //Ejercicio 3
   initial begin
    #100

    $display ("\n");
    $display ("Ejercicio 3, Contador de gray");
    $display ("-----------------------------");
    $display ("Co | A B C |  S  SF");
    $monitor ("%b  | %b %b %b | %b %b", co, A, B, C, E, EF);

    reset = 0; co = 0;
    #1 reset = 1;
    #1 reset = 0;
    #16 co = 1;
    #16 co = 0;

    $finish;
   end

   always
    #1 clk = ~clk;

    initial begin

      $dumpfile("Lab_06_tb.vcd");
      $dumpvars(0, testbench);

    end

endmodule

Lab 06/Lab_06_tb.vcd
$date
	Sat Sep 05 22:17:51 2020
$end
$version
	Icarus Verilog
$end
$timescale
	1ps
$end
$scope module testbench $end
$var wire 1 ! s1 $end
$var wire 4 " q [3:0] $end
$var wire 2 # ef [1:0] $end
$var wire 2 $ e [1:0] $end
$var wire 1 % EF $end
$var wire 3 & E [2:0] $end
$var wire 1 ' C $end
$var wire 1 ( B $end
$var wire 1 ) A $end
$var reg 1 * clk $end
$var reg 1 + co $end
$var reg 4 , d [3:0] $end
$var reg 1 - en $end
$var reg 1 . reset $end
$var reg 1 / v1 $end
$var reg 1 0 v2 $end
$scope module a1 $end
$var wire 1 * clk $end
$var wire 4 1 d [3:0] $end
$var wire 1 - en $end
$var wire 1 . reset $end
$var reg 4 2 q [3:0] $end
$upscope $end
$scope module a2 $end
$var wire 1 / A $end
$var wire 1 0 B $end
$var wire 1 * clk $end
$var wire 1 . reset $end
$var wire 1 ! y $end
$var wire 2 3 SF [1:0] $end
$var wire 2 4 S [1:0] $end
$scope module u0 $end
$var wire 1 * clk $end
$var wire 1 5 d $end
$var wire 1 . reset $end
$var reg 1 6 q $end
$upscope $end
$scope module u1 $end
$var wire 1 * clk $end
$var wire 1 7 d $end
$var wire 1 . reset $end
$var reg 1 8 q $end
$upscope $end
$upscope $end
$scope module a3 $end
$var wire 1 ( b $end
$var wire 1 ' c $end
$var wire 1 * clk $end
$var wire 1 + co $end
$var wire 1 . reset $end
$var wire 3 9 s_f [2:0] $end
$var wire 3 : s [2:0] $end
$var wire 1 ) a $end
$scope module S0 $end
$var wire 1 * clk $end
$var wire 1 ; d $end
$var wire 1 . reset $end
$var reg 1 < q $end
$upscope $end
$scope module S1 $end
$var wire 1 * clk $end
$var wire 1 = d $end
$var wire 1 . reset $end
$var reg 1 > q $end
$upscope $end
$scope module S2 $end
$var wire 1 * clk $end
$var wire 1 ? d $end
$var wire 1 . reset $end
$var reg 1 @ q $end
$upscope $end
$upscope $end
$upscope $end
$enddefinitions $end
#0
$dumpvars
x@
x?
x>
x=
x<
x;
bx :
bx 9
x8
x7
x6
x5
bx 4
bx 3
b0 2
b0 1
x0
x/
0.
1-
b0 ,
x+
1*
x)
x(
x'
bx &
x%
bx $
bx #
b0 "
x!
$end
#1
07
1;
1%
0'
0(
b0x #
b0x 3
0!
bx1 9
0)
0<
0>
b0 &
b0 :
0@
06
b0 $
b0 4
08
0*
1.
#2
x7
bx #
bx 3
x(
0;
0%
x'
bx0 9
x)
b0x $
b0x 4
x6
x@
x>
bx1 &
bx1 :
1<
1*
0.
#3
0*
#4
1;
1%
x!
bx1 9
bx0 &
bx0 :
0<
bx $
bx 4
x8
1*
#5
0*
#6
0;
0%
bx0 9
b111 "
b111 2
bx1 &
bx1 :
1<
1*
b111 ,
b111 1
#7
0*
#8
1;
1%
bx1 9
bx0 &
bx0 :
0<
1*
#9
0*
#10
0;
0%
bx0 9
b1101 "
b1101 2
bx1 &
bx1 :
1<
1*
b1101 ,
b1101 1
#11
0*
#12
1;
1%
bx1 9
bx0 &
bx0 :
0<
1*
#13
0*
#14
0;
0%
bx0 9
b111 "
b111 2
bx1 &
bx1 :
1<
1*
b111 ,
b111 1
#15
0*
#16
1;
1%
bx1 9
bx0 &
bx0 :
0<
1*
#17
0*
#18
0;
0%
bx0 9
b100 "
b100 2
bx1 &
bx1 :
1<
1*
b100 ,
b100 1
#19
0*
#20
1;
1%
bx1 9
bx0 &
bx0 :
0<
1*
#21
0*
#22
0;
0%
bx0 9
b111 "
b111 2
bx1 &
bx1 :
1<
1*
b111 ,
b111 1
#23
0*
#24
1;
1%
bx1 9
bx0 &
bx0 :
0<
1*
#25
0*
#26
0;
0%
bx0 9
b1100 "
b1100 2
bx1 &
bx1 :
1<
1*
b1100 ,
b1100 1
#27
0*
#28
1;
1%
bx1 9
bx0 &
bx0 :
0<
1*
#29
0*
#30
0;
0%
bx0 9
b110 "
b110 2
bx1 &
bx1 :
1<
1*
b110 ,
b110 1
#31
0*
#32
1;
1%
bx1 9
bx0 &
bx0 :
0<
1*
#33
0*
#34
0;
0%
bx0 9
bx1 &
bx1 :
1<
1*
#35
0*
#36
1;
1%
bx1 9
bx0 &
bx0 :
0<
1*
#37
0*
#38
0;
0%
bx0 9
bx1 &
bx1 :
1<
1*
#39
0*
#40
1;
1%
bx1 9
bx0 &
bx0 :
0<
07
05
0!
b0 #
b0 3
1*
00
0/
#41
0'
0(
0)
b0 "
b0 2
08
b0 $
b0 4
06
0@
b0 &
b0 :
0>
0*
1.
#42
0;
0%
x'
x(
bx0 9
x)
1<
x>
bx1 &
bx1 :
x@
b110 "
b110 2
1*
0.
#43
0*
#44
1;
1%
bx1 9
bx0 &
bx0 :
0<
1*
#45
0*
#46
0;
0%
bx0 9
bx1 &
bx1 :
1<
15
b1 #
b1 3
1*
1/
#47
0*
#48
05
b0 #
b0 3
1;
1%
bx1 9
b1 $
b1 4
16
bx0 &
bx0 :
0<
1*
#49
0*
#50
15
b1 #
b1 3
0;
0%
bx0 9
bx1 &
bx1 :
1<
b0 $
b0 4
06
1*
#51
0*
#52
05
b0 #
b0 3
1;
1%
bx1 9
b1 $
b1 4
16
bx0 &
bx0 :
0<
1*
#53
0*
#54
15
0;
0%
bx0 9
bx1 &
bx1 :
1<
b0 $
b0 4
06
07
b1 #
b1 3
1*
10
#55
0*
#56
05
17
b10 #
b10 3
1;
1%
bx1 9
b1 $
b1 4
16
bx0 &
bx0 :
0<
1*
#57
0*
#58
0;
0%
1!
bx0 9
bx1 &
bx1 :
1<
06
b10 $
b10 4
18
1*
#59
0*
#60
1;
1%
bx1 9
bx0 &
bx0 :
0<
1*
#61
0*
#62
0;
0%
bx0 9
bx1 &
bx1 :
1<
1*
#63
0*
#64
1;
1%
bx1 9
bx0 &
bx0 :
0<
1*
#65
0*
#66
0;
0%
bx0 9
bx1 &
bx1 :
1<
1*
#67
0*
#68
1;
1%
bx1 9
bx0 &
bx0 :
0<
1*
#69
0*
#70
0;
0%
bx0 9
bx1 &
bx1 :
1<
07
b0 #
b0 3
0!
1*
00
0/
#71
0*
#72
1;
1%
bx1 9
b0 $
b0 4
08
bx0 &
bx0 :
0<
1*
#73
0*
#74
0;
0%
bx0 9
bx1 &
bx1 :
1<
1*
#75
0*
#76
1;
1%
bx1 9
bx0 &
bx0 :
0<
1*
#77
0*
#78
0;
0%
bx0 9
bx1 &
bx1 :
1<
1*
#79
0*
#80
1;
1%
bx1 9
bx0 &
bx0 :
0<
1*
#81
0*
#82
0;
0%
bx0 9
bx1 &
bx1 :
1<
1*
#83
0*
#84
1;
1%
bx1 9
bx0 &
bx0 :
0<
1*
#85
0*
#86
0;
0%
bx0 9
bx1 &
bx1 :
1<
15
b1 #
b1 3
1*
10
1/
#87
0*
#88
05
17
b10 #
b10 3
1;
1%
bx1 9
b1 $
b1 4
16
bx0 &
bx0 :
0<
1*
#89
0*
#90
0;
0%
1!
bx0 9
bx1 &
bx1 :
1<
06
b10 $
b10 4
18
1*
#91
0*
#92
1;
1%
bx1 9
bx0 &
bx0 :
0<
1*
#93
0*
#94
0;
0%
bx0 9
bx1 &
bx1 :
1<
1*
#95
0*
#96
1;
1%
bx1 9
bx0 &
bx0 :
0<
1*
#97
0*
#98
0;
0%
bx0 9
bx1 &
bx1 :
1<
1*
#99
0*
#100
1;
1%
bx1 9
bx0 &
bx0 :
0<
1*
0+
#101
1?
1=
b111 9
15
07
b1 #
b1 3
0'
0(
0!
0)
0>
b0 &
b0 :
0@
b0 $
b0 4
08
b0 "
b0 2
0*
1.
#102
05
17
b10 #
b10 3
0(
0;
0%
0'
b110 9
1)
b110 "
b110 2
b1 $
b1 4
16
1@
1>
b111 &
b111 :
1<
1*
0.
#103
0*
#104
0=
1'
1;
1%
1!
b101 9
b110 &
b110 :
0<
06
b10 $
b10 4
18
1*
#105
0*
#106
1?
1(
1'
0;
0%
b100 9
0>
b101 &
b101 :
1<
1*
#107
0*
#108
1=
0?
1;
1%
0'
b11 9
b100 &
b100 :
0<
1*
#109
0*
#110
0;
0%
0'
b10 9
0)
0@
1>
b11 &
b11 :
1<
1*
#111
0*
#112
0=
1'
1;
1%
b1 9
b10 &
b10 :
0<
1*
#113
0*
#114
1'
0(
0;
0%
b0 9
0>
b1 &
b1 :
1<
1*
#115
0*
#116
1?
1=
1;
1%
0'
b111 9
b0 &
b0 :
0<
1*
#117
0*
#118
0(
0;
0%
0'
1)
1@
1>
b111 &
b111 :
1<
0?
0=
b0 9
1*
1+
#119
0*
#120
1;
1%
b1 9
0)
0<
0>
b0 &
b0 :
0@
1*
#121
0*
#122
1=
0;
0%
1'
b10 9
b1 &
b1 :
1<
1*
#123
0*
#124
1;
1%
1(
b11 9
0<
b10 &
b10 :
1>
1*
#125
0*
#126
1?
0=
0'
0;
0%
b100 9
b11 &
b11 :
1<
1*
#127
0*
#128
1;
1%
1(
b101 9
1)
0<
0>
b100 &
b100 :
1@
1*
#129
0*
#130
1=
0;
0%
1'
b110 9
b101 &
b101 :
1<
1*
#131
0*
#132
0(
1;
1%
b111 9
0<
b110 &
b110 :
1>
1*
#133
0*
#134
1?
0'
0;
0%
b111 &
b111 :
1<
1=
b110 9
1*
0+
