Lab 09/Eje 03/Eje03.v
module ffd(input clk, input reset, input en, input d, output reg q);

  always @ (posedge clk, posedge reset)
  if (reset) q <= 1'b0;
  else if (en == 1) q <= d;

endmodule

module ffjk(input clk, reset, en, j, k, output q);

  wire d;

  assign d = (~k & q) | (j & ~q);

  ffd a1(clk, reset, en, d, q);

endmodule

Lab 09/Eje 03/Eje03_tb.v
module testbench();

  reg clk, reset, en, j, k;
  wire q;

  ffjk a1(clk, reset, en, j, k, q);

  initial begin
    #1

    clk = 0; reset = 0; en = 1; j = 0; k = 0;
    $display("Ejercicio 3: Flip Flop JK");
    $display("J | K | Q");
    $monitor("%b | %b | %b", j, k, q);
    #1 reset = 1;
    #1 reset = 0;
    #3 k = 1;
    #10 j = 1; k = 0;
    #10 k = 1;

    #30 $finish;
    end

  always
  begin
    #1 clk = ~clk;
    end

  initial begin
    $dumpfile("Eje03_tb.vcd");
    $dumpvars(0, testbench);
  end


endmodule

Lab 09/Eje 03/Eje03_tb.vcd
$date
	Fri Oct 30 22:02:24 2020
$end
$version
	Icarus Verilog
$end
$timescale
	1ps
$end
$scope module testbench $end
$var wire 1 ! q $end
$var reg 1 " clk $end
$var reg 1 # en $end
$var reg 1 $ j $end
$var reg 1 % k $end
$var reg 1 & reset $end
$scope module a1 $end
$var wire 1 " clk $end
$var wire 1 ' d $end
$var wire 1 # en $end
$var wire 1 $ j $end
$var wire 1 % k $end
$var wire 1 & reset $end
$var wire 1 ! q $end
$scope module a1 $end
$var wire 1 " clk $end
$var wire 1 ' d $end
$var wire 1 # en $end
$var wire 1 & reset $end
$var reg 1 ! q $end
$upscope $end
$upscope $end
$upscope $end
$enddefinitions $end
#0
$dumpvars
x'
x&
x%
x$
x#
x"
x!
$end
#1
0%
0$
1#
0&
1"
#2
0'
0!
0"
1&
#3
1"
0&
#4
0"
#5
1"
#6
0"
1%
#7
1"
#8
0"
#9
1"
#10
0"
#11
1"
#12
0"
#13
1"
#14
0"
#15
1"
#16
1'
0"
0%
1$
#17
1!
1"
#18
0"
#19
1"
#20
0"
#21
1"
#22
0"
#23
1"
#24
0"
#25
1"
#26
0'
0"
1%
#27
1'
0!
1"
#28
0"
#29
0'
1!
1"
#30
0"
#31
1'
0!
1"
#32
0"
#33
0'
1!
1"
#34
0"
#35
1'
0!
1"
#36
0"
#37
0'
1!
1"
#38
0"
#39
1'
0!
1"
#40
0"
#41
0'
1!
1"
#42
0"
#43
1'
0!
1"
#44
0"
#45
0'
1!
1"
#46
0"
#47
1'
0!
1"
#48
0"
#49
0'
1!
1"
#50
0"
#51
1'
0!
1"
#52
0"
#53
0'
1!
1"
#54
0"
#55
1'
0!
1"
