Lab 09/Eje 02/Eje_02.v
module ffd(input clk, input reset, input en, input d, output reg q);

  always @ (posedge clk, posedge reset)
  if (reset) q <= 1'b0;
  else if (en) q <= d;

endmodule

module fft(input clk, en, reset, output q);

  wire w;
  assign w = ~q;

  ffd a(clk, reset, en, w, q);

endmodule

Lab 09/Eje 02/Eje_02_tb.v
module testbench();

  reg clk, reset, en;
  wire q;

  fft a(clk, en, reset, q);

  initial begin

  #1
  clk = 0; en = 1; reset = 0;
  $display("Ejercicio 02: Flip FLop T");
  $display("| Q |");
  $monitor("| %b |", q);
  #1 reset = 1;
  #1 reset = 0;

  #20 $finish;
  end

  always
   #1 clk = ~clk;

   initial begin
     $dumpfile("Eje_02_tb.vcd");
     $dumpvars(0, testbench);
   end

endmodule

Lab 09/Eje 02/Eje_02_tb.vcd
$date
	Thu Oct 29 12:04:53 2020
$end
$version
	Icarus Verilog
$end
$timescale
	1ps
$end
$scope module testbench $end
$var wire 1 ! q $end
$var reg 1 " clk $end
$var reg 1 # en $end
$var reg 1 $ reset $end
$scope module a $end
$var wire 1 " clk $end
$var wire 1 # en $end
$var wire 1 $ reset $end
$var wire 1 % w $end
$var wire 1 ! q $end
$scope module a $end
$var wire 1 " clk $end
$var wire 1 % d $end
$var wire 1 # en $end
$var wire 1 $ reset $end
$var reg 1 ! q $end
$upscope $end
$upscope $end
$upscope $end
$enddefinitions $end
#0
$dumpvars
x%
x$
x#
x"
x!
$end
#1
0$
1#
1"
#2
1%
0!
0"
1$
#3
0%
1!
1"
0$
#4
0"
#5
1%
0!
1"
#6
0"
#7
0%
1!
1"
#8
0"
#9
1%
0!
1"
#10
0"
#11
0%
1!
1"
#12
0"
#13
1%
0!
1"
#14
0"
#15
0%
1!
1"
#16
0"
#17
1%
0!
1"
#18
0"
#19
0%
1!
1"
#20
0"
#21
1%
0!
1"
#22
0"
#23
0%
1!
1"
