Lab 04/Lab4.v


module tabla1(input wire A, B, C, output wire Y);

  assign Y = (~A & ~C) | (A & ~B) | (A & C);

endmodule

module tabla2(input wire A, B, C, output wire Y);

  not (Y, B);

endmodule

module tabla3(input wire A, B, C, D, output wire Y);

  assign Y = (~A & ~B & ~C & ~D) | (~A & ~B & C & D) | (~A & B & ~C & D) | (~A & B & C & ~D) | (A & B & ~C & ~D) | (A & B & C & D) | (A & ~B & ~C & D) | (A & ~B & C & ~D);

endmodule

module tabla4(input wire A, B, C, D, output wire Y);

  assign Y = (A & B) | (A & C) | (A & ~D);

endmodule

module tabla5(input wire A, B, C, D, output wire Y);

  assign Y = (A & ~B) | (A & ~C) | (A & ~D) | (~B & ~C & ~D);

endmodule

module tabla6(input wire A, B, C, output wire Y);

  not(n1, B);
  or (Y, n1, C);

endmodule

module tabla7(input wire A, B, C, D, output wire Y);

  not (n2, C);
  and (n3, n1, D);
  and (n4, A, D);
  or  (Y, B, n3, n4);

endmodule

module tabla8(input wire A, B, C, output wire Y);

  not (n5, A);
  not (n6, C);
  and (n7, n5, n6);
  or  (Y, n7, B);

endmodule

Lab 04/Lab4_tb.v
module testbench();

  reg p1, p2, p3, p4, p5, p6, p7, p8, p9, p10, p11, p12, p13, p14, p15, p16, p17, p18, p19, p20, p21, p22, p23, p24, p25, p26, p27, p28;
  wire s1, s2, s3, s4, s5, s6, s7, s8;

  tabla1 t1(p1, p2, p3, s1);
  tabla2 t2(p4, p5, p6, s2);
  tabla3 t3(p7, p8, p9, p10, s3);
  tabla4 t4(p11, p12, p13, p14, s4);
  tabla5 t5(p15, p16, p17, p18, s5);
  tabla6 t6(p19, p20, p21, s6);
  tabla7 t7(p22, p23, p24, p25, s7);
  tabla8 t8(p26, p27, p28, s8);

  initial begin

    $display("Ejercicio 1, Tabla 1");
    $display("A B C | Y");
    $monitor("%b %b %b | %b", p1, p2, p3, s1);

       p1 = 0; p2 = 0; p3 = 0;
    #1 p1 = 0; p2 = 0; p3 = 1;
    #1 p1 = 0; p2 = 1; p3 = 0;
    #1 p1 = 0; p2 = 1; p3 = 1;
    #1 p1 = 1; p2 = 0; p3 = 0;
    #1 p1 = 1; p2 = 0; p3 = 1;
    #1 p1 = 1; p2 = 1; p3 = 0;
    #1 p1 = 1; p2 = 1; p3 = 1;

  end

  initial begin

    #9

    $display("\n");
    $display("Ejercicio 1, Tabla 2");
    $display("A B C | Y");
    $monitor("%b %b %b | %b", p4, p5, p6, s2);

       p4 = 0; p5 = 0; p6 = 0;
    #1 p4 = 0; p5 = 0; p6 = 1;
    #1 p4 = 0; p5 = 1; p6 = 0;
    #1 p4 = 0; p5 = 1; p6 = 1;
    #1 p4 = 1; p5 = 0; p6 = 0;
    #1 p4 = 1; p5 = 0; p6 = 1;
    #1 p4 = 1; p5 = 1; p6 = 0;
    #1 p4 = 1; p5 = 1; p6 = 1;

  end

  initial begin

    #18

    $display("\n");
    $display("Ejercicio 1, Tabla 3");
    $display("A B C D | Y");
    $monitor("%b %b %b %b | %b", p7, p8, p9, p10, s3);

       p7 = 0; p8 = 0; p9 = 0; p10 = 0;
    #1 p7 = 0; p8 = 0; p9 = 0; p10 = 1;
    #1 p7 = 0; p8 = 0; p9 = 1; p10 = 0;
    #1 p7 = 0; p8 = 0; p9 = 1; p10 = 1;
    #1 p7 = 0; p8 = 1; p9 = 0; p10 = 0;
    #1 p7 = 0; p8 = 1; p9 = 0; p10 = 1;
    #1 p7 = 0; p8 = 1; p9 = 1; p10 = 0;
    #1 p7 = 0; p8 = 1; p9 = 1; p10 = 1;
    #1 p7 = 1; p8 = 0; p9 = 0; p10 = 0;
    #1 p7 = 1; p8 = 0; p9 = 0; p10 = 1;
    #1 p7 = 1; p8 = 0; p9 = 1; p10 = 0;
    #1 p7 = 1; p8 = 0; p9 = 1; p10 = 1;
    #1 p7 = 1; p8 = 1; p9 = 0; p10 = 0;
    #1 p7 = 1; p8 = 1; p9 = 0; p10 = 1;
    #1 p7 = 1; p8 = 1; p9 = 1; p10 = 0;
    #1 p7 = 1; p8 = 1; p9 = 1; p10 = 1;

  end

  initial begin

    #35

    $display("\n");
    $display("Ejercicio 1, Tabla 4");
    $display("A B C D | Y");
    $monitor("%b %b %b %b | %b", p11, p12, p13, p14, s4);

       p11 = 0; p12 = 0; p13 = 0; p14 = 0;
    #1 p11 = 0; p12 = 0; p13 = 0; p14 = 1;
    #1 p11 = 0; p12 = 0; p13 = 1; p14 = 0;
    #1 p11 = 0; p12 = 0; p13 = 1; p14 = 1;
    #1 p11 = 0; p12 = 1; p13 = 0; p14 = 0;
    #1 p11 = 0; p12 = 1; p13 = 0; p14 = 1;
    #1 p11 = 0; p12 = 1; p13 = 1; p14 = 0;
    #1 p11 = 0; p12 = 1; p13 = 1; p14 = 1;
    #1 p11 = 1; p12 = 0; p13 = 0; p14 = 0;
    #1 p11 = 1; p12 = 0; p13 = 0; p14 = 1;
    #1 p11 = 1; p12 = 0; p13 = 1; p14 = 0;
    #1 p11 = 1; p12 = 0; p13 = 1; p14 = 1;
    #1 p11 = 1; p12 = 1; p13 = 0; p14 = 0;
    #1 p11 = 1; p12 = 1; p13 = 0; p14 = 1;
    #1 p11 = 1; p12 = 1; p13 = 1; p14 = 0;
    #1 p11 = 1; p12 = 1; p13 = 1; p14 = 1;

  end

  initial begin

    #52

    $display("\n");
    $display("Ejercicio 2, Tabla 1");
    $display("A B C D | Y");
    $monitor("%b %b %b %b | %b", p15, p16, p17, p18, s5);

       p15 = 0; p16 = 0; p17 = 0; p18 = 0;
    #1 p15 = 0; p16 = 0; p17 = 0; p18 = 1;
    #1 p15 = 0; p16 = 0; p17 = 1; p18 = 0;
    #1 p15 = 0; p16 = 0; p17 = 1; p18 = 1;
    #1 p15 = 0; p16 = 1; p17 = 0; p18 = 0;
    #1 p15 = 0; p16 = 1; p17 = 0; p18 = 1;
    #1 p15 = 0; p16 = 1; p17 = 1; p18 = 0;
    #1 p15 = 0; p16 = 1; p17 = 1; p18 = 1;
    #1 p15 = 1; p16 = 0; p17 = 0; p18 = 0;
    #1 p15 = 1; p16 = 0; p17 = 0; p18 = 1;
    #1 p15 = 1; p16 = 0; p17 = 1; p18 = 0;
    #1 p15 = 1; p16 = 0; p17 = 1; p18 = 1;
    #1 p15 = 1; p16 = 1; p17 = 0; p18 = 0;
    #1 p15 = 1; p16 = 1; p17 = 0; p18 = 1;
    #1 p15 = 1; p16 = 1; p17 = 1; p18 = 0;
    #1 p15 = 1; p16 = 1; p17 = 1; p18 = 1;

  end

  initial begin

    #69

    $display("\n");
    $display("Ejercicio 2, Tabla 2");
    $display("A B C | Y");
    $monitor("%b %b %b | %b", p19, p20, p21, s6);

       p19 = 0; p20 = 0; p21 = 0;
    #1 p19 = 0; p20 = 0; p21 = 1;
    #1 p19 = 0; p20 = 1; p21 = 0;
    #1 p19 = 0; p20 = 1; p21 = 1;
    #1 p19 = 1; p20 = 0; p21 = 0;
    #1 p19 = 1; p20 = 0; p21 = 1;
    #1 p19 = 1; p20 = 1; p21 = 0;
    #1 p19 = 1; p20 = 1; p21 = 1;

  end

  initial begin

    #78

    $display("\n");
    $display("Ejercicio 2, Tabla 3");
    $display("A B C D | Y");
    $monitor("%b %b %b %b | %b", p22, p23, p24, p25, s7);

       p22 = 0; p23 = 0; p24 = 0; p25 = 0;
    #1 p22 = 0; p23 = 0; p24 = 0; p25 = 1;
    #1 p22 = 0; p23 = 0; p24 = 1; p25 = 0;
    #1 p22 = 0; p23 = 0; p24 = 1; p25 = 1;
    #1 p22 = 0; p23 = 1; p24 = 0; p25 = 0;
    #1 p22 = 0; p23 = 1; p24 = 0; p25 = 1;
    #1 p22 = 0; p23 = 1; p24 = 1; p25 = 0;
    #1 p22 = 0; p23 = 1; p24 = 1; p25 = 1;
    #1 p22 = 1; p23 = 0; p24 = 0; p25 = 0;
    #1 p22 = 1; p23 = 0; p24 = 0; p25 = 1;
    #1 p22 = 1; p23 = 0; p24 = 1; p25 = 0;
    #1 p22 = 1; p23 = 0; p24 = 1; p25 = 1;
    #1 p22 = 1; p23 = 1; p24 = 0; p25 = 0;
    #1 p22 = 1; p23 = 1; p24 = 0; p25 = 1;
    #1 p22 = 1; p23 = 1; p24 = 1; p25 = 0;
    #1 p22 = 1; p23 = 1; p24 = 1; p25 = 1;

  end

  initial begin

    #95

    $display("\n");
    $display("Ejercicio 2, Tabla 4");
    $display("A B C | Y");
    $monitor("%b %b %b | %b", p26, p27, p28, s8);

       p26 = 0; p27 = 0; p28 = 0;
    #1 p26 = 0; p27 = 0; p28 = 1;
    #1 p26 = 0; p27 = 1; p28 = 0;
    #1 p26 = 0; p27 = 1; p28 = 1;
    #1 p26 = 1; p27 = 0; p28 = 0;
    #1 p26 = 1; p27 = 0; p28 = 1;
    #1 p26 = 1; p27 = 1; p28 = 0;
    #1 p26 = 1; p27 = 1; p28 = 1;

  end

  initial
  #105 $finish;

  initial begin

    $dumpfile("Lab4_tb.vcd");
    $dumpvars(0, testbench);

  end

endmodule

Lab 04/Lab4_tb.vcd
$date
	Fri Aug 07 21:15:14 2020
$end
$version
	Icarus Verilog
$end
$timescale
	1ps
$end
$scope module testbench $end
$var wire 1 ! s8 $end
$var wire 1 " s7 $end
$var wire 1 # s6 $end
$var wire 1 $ s5 $end
$var wire 1 % s4 $end
$var wire 1 & s3 $end
$var wire 1 ' s2 $end
$var wire 1 ( s1 $end
$var reg 1 ) p1 $end
$var reg 1 * p10 $end
$var reg 1 + p11 $end
$var reg 1 , p12 $end
$var reg 1 - p13 $end
$var reg 1 . p14 $end
$var reg 1 / p15 $end
$var reg 1 0 p16 $end
$var reg 1 1 p17 $end
$var reg 1 2 p18 $end
$var reg 1 3 p19 $end
$var reg 1 4 p2 $end
$var reg 1 5 p20 $end
$var reg 1 6 p21 $end
$var reg 1 7 p22 $end
$var reg 1 8 p23 $end
$var reg 1 9 p24 $end
$var reg 1 : p25 $end
$var reg 1 ; p26 $end
$var reg 1 < p27 $end
$var reg 1 = p28 $end
$var reg 1 > p3 $end
$var reg 1 ? p4 $end
$var reg 1 @ p5 $end
$var reg 1 A p6 $end
$var reg 1 B p7 $end
$var reg 1 C p8 $end
$var reg 1 D p9 $end
$scope module t1 $end
$var wire 1 ) A $end
$var wire 1 4 B $end
$var wire 1 > C $end
$var wire 1 ( Y $end
$upscope $end
$scope module t2 $end
$var wire 1 ? A $end
$var wire 1 @ B $end
$var wire 1 A C $end
$var wire 1 ' Y $end
$upscope $end
$scope module t3 $end
$var wire 1 B A $end
$var wire 1 C B $end
$var wire 1 D C $end
$var wire 1 * D $end
$var wire 1 & Y $end
$upscope $end
$scope module t4 $end
$var wire 1 + A $end
$var wire 1 , B $end
$var wire 1 - C $end
$var wire 1 . D $end
$var wire 1 % Y $end
$upscope $end
$scope module t5 $end
$var wire 1 / A $end
$var wire 1 0 B $end
$var wire 1 1 C $end
$var wire 1 2 D $end
$var wire 1 $ Y $end
$upscope $end
$scope module t6 $end
$var wire 1 3 A $end
$var wire 1 5 B $end
$var wire 1 6 C $end
$var wire 1 # Y $end
$var wire 1 E n1 $end
$upscope $end
$scope module t7 $end
$var wire 1 7 A $end
$var wire 1 8 B $end
$var wire 1 9 C $end
$var wire 1 : D $end
$var wire 1 " Y $end
$var wire 1 F n1 $end
$var wire 1 G n2 $end
$var wire 1 H n3 $end
$var wire 1 I n4 $end
$upscope $end
$scope module t8 $end
$var wire 1 ; A $end
$var wire 1 < B $end
$var wire 1 = C $end
$var wire 1 ! Y $end
$var wire 1 J n5 $end
$var wire 1 K n6 $end
$var wire 1 L n7 $end
$upscope $end
$upscope $end
$enddefinitions $end
#0
$dumpvars
xL
xK
xJ
xI
xH
xG
zF
xE
xD
xC
xB
xA
x@
x?
0>
x=
x<
x;
x:
x9
x8
x7
x6
x5
04
x3
x2
x1
x0
x/
x.
x-
x,
x+
x*
0)
1(
x'
x&
x%
x$
x#
x"
x!
$end
#1
0(
1>
#2
1(
0>
14
#3
0(
1>
#4
1(
0>
04
1)
#5
1>
#6
0(
0>
14
#7
1(
1>
#9
1'
0A
0@
0?
#10
1A
#11
0'
0A
1@
#12
1A
#13
1'
0A
0@
1?
#14
1A
#15
0'
0A
1@
#16
1A
#18
1&
0*
0D
0C
0B
#19
0&
1*
#20
0*
1D
#21
1&
1*
#22
0&
0*
0D
1C
#23
1&
1*
#24
0*
1D
#25
0&
1*
#26
0*
0D
0C
1B
#27
1&
1*
#28
0*
1D
#29
0&
1*
#30
1&
0*
0D
1C
#31
0&
1*
#32
0*
1D
#33
1&
1*
#35
0%
0.
0-
0,
0+
#36
1.
#37
0.
1-
#38
1.
#39
0.
0-
1,
#40
1.
#41
0.
1-
#42
1.
#43
1%
0.
0-
0,
1+
#44
0%
1.
#45
1%
0.
1-
#46
1.
#47
0.
0-
1,
#48
1.
#49
0.
1-
#50
1.
#52
1$
02
01
00
0/
#53
0$
12
#54
02
11
#55
12
#56
02
01
10
#57
12
#58
02
11
#59
12
#60
1$
02
01
00
1/
#61
12
#62
02
11
#63
12
#64
02
01
10
#65
12
#66
02
11
#67
0$
12
#69
1#
1E
06
05
03
#70
16
#71
0#
0E
06
15
#72
1#
16
#73
1E
06
05
13
#74
16
#75
0#
0E
06
15
#76
1#
16
#78
0"
0H
1G
0I
0:
09
08
07
#79
x"
xH
1:
#80
0"
0H
0G
0:
19
#81
x"
xH
1:
#82
0H
1G
1"
0:
09
18
#83
xH
1:
#84
0H
0G
0:
19
#85
xH
1:
#86
0H
1G
0"
0:
09
08
17
#87
1"
xH
1I
1:
#88
0"
0H
0I
0G
0:
19
#89
1"
xH
1I
1:
#90
0H
0I
1G
0:
09
18
#91
xH
1I
1:
#92
0H
0I
0G
0:
19
#93
xH
1I
1:
#95
1!
1L
1K
1J
0=
0<
0;
#96
0!
0L
0K
1=
#97
1L
1K
1!
0=
1<
#98
0L
0K
1=
#99
1K
0!
0J
0=
0<
1;
#100
0K
1=
#101
1K
1!
0=
1<
#102
0K
1=
